<character>
  <points name="山-shu">
    <point pos="1" y="206.625" x="386.75"/>
    <point pos="0" y="206.5" x="387.25"/>
    <point pos="0" y="206.375" x="387.375"/>
    <point pos="0" y="206.5" x="387.375"/>
    <point pos="0" y="206.75" x="387.375"/>
    <point pos="0" y="214.75" x="388.125"/>
    <point pos="0" y="224.375" x="390.125"/>
    <point pos="0" y="236.75" x="396.625"/>
    <point pos="0" y="242.5" x="398.25"/>
    <point pos="0" y="242.875" x="398.375"/>
    <point pos="0" y="253.5" x="400.5"/>
    <point pos="0" y="265.125" x="401.5"/>
    <point pos="0" y="270.375" x="402.625"/>
    <point pos="0" y="277.625" x="404.875"/>
    <point pos="0" y="279.25" x="406.125"/>
    <point pos="0" y="280.5" x="408.5"/>
    <point pos="0" y="280.625" x="408.625"/>
    <point pos="0" y="281.75" x="411.875"/>
    <point pos="0" y="281.625" x="416.25"/>
    <point pos="0" y="281.375" x="416.375"/>
    <point pos="0" y="281" x="416.25"/>
    <point pos="0" y="279.5" x="415"/>
    <point pos="2" y="281" x="416.625"/>
    <point pos="0" y="281" x="416.5"/>
    <point pos="0" y="281.125" x="416.75"/>
    <point pos="0" y="281.125" x="416.875"/>
    <point pos="0" y="281.125" x="417"/>
    <point pos="0" y="280.125" x="418"/>
    <point pos="0" y="276.875" x="418.875"/>
    <point pos="0" y="270.125" x="417.5"/>
    <point pos="0" y="257.375" x="417.5"/>
    <point pos="0" y="251.625" x="417"/>
    <point pos="0" y="244.875" x="417.25"/>
    <point pos="0" y="238.125" x="416.75"/>
    <point pos="0" y="231.25" x="415.375"/>
    <point pos="0" y="230.75" x="415.25"/>
    <point pos="0" y="225.5" x="413.875"/>
    <point pos="0" y="223.75" x="412.375"/>
    <point pos="0" y="216.375" x="401.5"/>
    <point pos="0" y="215.125" x="398.25"/>
    <point pos="0" y="211.125" x="393.5"/>
    <point pos="0" y="211" x="393.25"/>
    <point pos="0" y="206.875" x="388.75"/>
    <point pos="0" y="206.625" x="387.75"/>
    <point pos="0" y="206.25" x="387"/>
  </points>
  <points name="shuheng">
    <point pos="1" y="256.5" x="357.5"/>
    <point pos="0" y="256.375" x="357.375"/>
    <point pos="0" y="256.125" x="357.5"/>
    <point pos="0" y="255.125" x="358.625"/>
    <point pos="0" y="254.625" x="360.125"/>
    <point pos="0" y="256.875" x="362.25"/>
    <point pos="0" y="258.875" x="363.375"/>
    <point pos="0" y="265.125" x="370.5"/>
    <point pos="0" y="268.125" x="375.75"/>
    <point pos="0" y="270.125" x="376.75"/>
    <point pos="0" y="276" x="375.25"/>
    <point pos="0" y="276.125" x="375.25"/>
    <point pos="0" y="277.625" x="374.875"/>
    <point pos="0" y="278" x="374.75"/>
    <point pos="0" y="280.25" x="373.5"/>
    <point pos="0" y="284.125" x="373.125"/>
    <point pos="0" y="288.625" x="370.5"/>
    <point pos="0" y="289.875" x="370.625"/>
    <point pos="0" y="290.75" x="372.125"/>
    <point pos="0" y="287.375" x="380.125"/>
    <point pos="0" y="287.125" x="380.375"/>
    <point pos="0" y="284" x="389.25"/>
    <point pos="0" y="282.375" x="390.75"/>
    <point pos="0" y="281.125" x="393"/>
    <point pos="0" y="277.875" x="404"/>
    <point pos="0" y="275.125" x="408.125"/>
    <point pos="0" y="274" x="413.375"/>
    <point pos="0" y="271.625" x="418.125"/>
    <point pos="0" y="268.75" x="422.25"/>
    <point pos="0" y="268.5" x="422.375"/>
    <point pos="0" y="264.375" x="425.625"/>
    <point pos="0" y="260.875" x="426.125"/>
    <point pos="0" y="258" x="427.25"/>
    <point pos="0" y="258.125" x="427.25"/>
    <point pos="0" y="258.375" x="426.625"/>
    <point pos="2" y="258.75" x="427"/>
    <point pos="0" y="258.5" x="426.875"/>
    <point pos="0" y="259" x="427.625"/>
    <point pos="0" y="262.375" x="431.5"/>
    <point pos="0" y="264.5" x="437.25"/>
    <point pos="0" y="266.25" x="440.125"/>
    <point pos="0" y="270.375" x="444.625"/>
    <point pos="0" y="272" x="445.75"/>
    <point pos="0" y="274.625" x="446.625"/>
    <point pos="0" y="278.75" x="445.75"/>
    <point pos="0" y="280.125" x="444"/>
    <point pos="0" y="280.375" x="440.375"/>
    <point pos="0" y="280.375" x="440.125"/>
    <point pos="0" y="280.25" x="437.875"/>
    <point pos="0" y="281.25" x="434.375"/>
    <point pos="0" y="281.5" x="431"/>
    <point pos="0" y="283.625" x="426.375"/>
    <point pos="0" y="284" x="423.75"/>
    <point pos="0" y="286.375" x="418.875"/>
    <point pos="0" y="288.125" x="416.875"/>
    <point pos="0" y="290.25" x="413.25"/>
    <point pos="0" y="290.875" x="411.125"/>
    <point pos="0" y="293" x="408.25"/>
    <point pos="0" y="295" x="403.875"/>
    <point pos="0" y="295.125" x="403.625"/>
    <point pos="0" y="299.75" x="387"/>
    <point pos="0" y="302" x="384.125"/>
    <point pos="0" y="307.25" x="375.125"/>
    <point pos="0" y="308.375" x="374"/>
    <point pos="0" y="310" x="368.75"/>
    <point pos="0" y="312.5" x="364.625"/>
    <point pos="0" y="312.875" x="364.25"/>
    <point pos="0" y="317.875" x="358.125"/>
    <point pos="0" y="318.25" x="356.375"/>
    <point pos="0" y="315.25" x="353.875"/>
    <point pos="0" y="313.75" x="351.625"/>
    <point pos="0" y="310.5" x="348.375"/>
    <point pos="0" y="307" x="346.5"/>
    <point pos="0" y="302.25" x="345.625"/>
    <point pos="0" y="298.625" x="346.125"/>
    <point pos="0" y="295.25" x="347.875"/>
    <point pos="0" y="294.875" x="348"/>
    <point pos="0" y="292" x="350.25"/>
    <point pos="0" y="288.75" x="354.625"/>
    <point pos="0" y="285.625" x="356.5"/>
    <point pos="0" y="278" x="359.25"/>
    <point pos="0" y="273.125" x="359.625"/>
    <point pos="0" y="266.25" x="361.25"/>
    <point pos="0" y="262.75" x="360.875"/>
    <point pos="0" y="260.25" x="359.625"/>
    <point pos="0" y="260.125" x="359.5"/>
    <point pos="0" y="258.375" x="358.125"/>
    <point pos="0" y="257.625" x="358.5"/>
    <point pos="0" y="257.125" x="358.625"/>
    <point pos="0" y="256.625" x="359"/>
    <point pos="0" y="256.125" x="359.25"/>
    <point pos="0" y="255.75" x="359.5"/>
    <point pos="0" y="255.375" x="359.625"/>
    <point pos="0" y="254.875" x="359.75"/>
    <point pos="0" y="254.75" x="359.875"/>
    <point pos="0" y="254.625" x="359.875"/>
    <point pos="0" y="254.5" x="359.875"/>
    <point pos="0" y="254.5" x="359.875"/>
    <point pos="0" y="254.5" x="359.875"/>
    <point pos="0" y="254.375" x="359.875"/>
    <point pos="0" y="254.375" x="359.875"/>
    <point pos="0" y="254.5" x="359.5"/>
    <point pos="0" y="254.625" x="359.25"/>
  </points>
  <points name="shu">
    <point pos="1" y="220" x="425"/>
    <point pos="0" y="220" x="424.75"/>
    <point pos="0" y="220" x="424.625"/>
    <point pos="0" y="219.875" x="424.625"/>
    <point pos="0" y="219.375" x="424.625"/>
    <point pos="0" y="219.25" x="424.625"/>
    <point pos="0" y="219.375" x="424.875"/>
    <point pos="0" y="219.5" x="425.5"/>
    <point pos="0" y="221.125" x="427.375"/>
    <point pos="0" y="224.25" x="429.625"/>
    <point pos="0" y="228.75" x="432.125"/>
    <point pos="0" y="232.375" x="433.5"/>
    <point pos="0" y="243.125" x="436.375"/>
    <point pos="0" y="247.125" x="436.625"/>
    <point pos="0" y="255.625" x="438.75"/>
    <point pos="0" y="265.5" x="440"/>
    <point pos="0" y="265.75" x="440"/>
    <point pos="0" y="268.25" x="440.375"/>
    <point pos="0" y="268.875" x="440.375"/>
    <point pos="0" y="269.125" x="440.375"/>
    <point pos="0" y="269.375" x="440.375"/>
    <point pos="0" y="269.75" x="440.25"/>
    <point pos="0" y="270.375" x="440.125"/>
    <point pos="0" y="270.875" x="440.25"/>
    <point pos="0" y="271.375" x="440.25"/>
    <point pos="0" y="271.625" x="440.25"/>
    <point pos="0" y="272.125" x="440.125"/>
    <point pos="0" y="273" x="440.25"/>
    <point pos="0" y="273.625" x="440.375"/>
    <point pos="0" y="274" x="440.375"/>
    <point pos="0" y="274.875" x="440.375"/>
    <point pos="0" y="275.375" x="440.25"/>
    <point pos="0" y="275.5" x="440.25"/>
    <point pos="0" y="275.625" x="440.125"/>
    <point pos="0" y="275.75" x="440.125"/>
    <point pos="0" y="276" x="440.125"/>
    <point pos="0" y="276.375" x="440.125"/>
    <point pos="0" y="277" x="440.125"/>
    <point pos="0" y="277.625" x="440.125"/>
    <point pos="0" y="278.25" x="440"/>
    <point pos="0" y="278.75" x="439.875"/>
    <point pos="0" y="279" x="439.875"/>
    <point pos="0" y="279.375" x="439.75"/>
    <point pos="0" y="279.875" x="439.75"/>
    <point pos="0" y="280.125" x="439.625"/>
    <point pos="0" y="280.25" x="439.625"/>
    <point pos="0" y="283.875" x="437.5"/>
    <point pos="0" y="284.625" x="436.625"/>
    <point pos="0" y="284.875" x="433.625"/>
    <point pos="0" y="283.875" x="429.875"/>
    <point pos="2" y="283.5" x="430"/>
    <point pos="0" y="283.5" x="429.75"/>
    <point pos="0" y="283.5" x="430.25"/>
    <point pos="0" y="283.625" x="430.25"/>
    <point pos="0" y="283.75" x="430.25"/>
    <point pos="0" y="283.875" x="430.25"/>
    <point pos="0" y="284" x="430.375"/>
    <point pos="0" y="284.125" x="430.5"/>
    <point pos="0" y="285.25" x="433.25"/>
    <point pos="0" y="289.25" x="438.875"/>
    <point pos="0" y="289" x="442.625"/>
    <point pos="0" y="289.5" x="448.875"/>
    <point pos="0" y="287" x="454.875"/>
    <point pos="0" y="285.875" x="456.625"/>
    <point pos="0" y="286" x="458.125"/>
    <point pos="0" y="286" x="458.25"/>
    <point pos="0" y="286.125" x="459.5"/>
    <point pos="0" y="285.5" x="460"/>
    <point pos="0" y="278.5" x="460.375"/>
    <point pos="0" y="275.125" x="461.25"/>
    <point pos="0" y="267.75" x="461.25"/>
    <point pos="0" y="263.875" x="460.25"/>
    <point pos="0" y="255.125" x="460.125"/>
    <point pos="0" y="250.75" x="459.25"/>
    <point pos="0" y="250.375" x="459.125"/>
    <point pos="0" y="249.875" x="459.125"/>
    <point pos="0" y="249.5" x="459"/>
    <point pos="0" y="247.375" x="458.625"/>
    <point pos="0" y="247" x="458.625"/>
    <point pos="0" y="240.5" x="455.75"/>
    <point pos="0" y="236" x="455.125"/>
    <point pos="0" y="229.875" x="452.875"/>
    <point pos="0" y="226" x="448.75"/>
    <point pos="0" y="223.75" x="447.5"/>
    <point pos="0" y="220" x="444.375"/>
    <point pos="0" y="217.625" x="440.125"/>
    <point pos="0" y="218" x="431.875"/>
    <point pos="0" y="218.875" x="427.5"/>
    <point pos="0" y="219.125" x="427.125"/>
    <point pos="0" y="219.375" x="425.5"/>
    <point pos="0" y="219.375" x="425.875"/>
    <point pos="0" y="219.5" x="426.5"/>
  </points>
</character>